discourse_client_in_disraptor/__init__.py
discourse_client_in_disraptor/discourse_api_client.py
discourse_client_in_disraptor/third_party_integrations.py
discourse_client_in_disraptor-0.0.10.dist-info/METADATA
discourse_client_in_disraptor-0.0.10.dist-info/WHEEL
discourse_client_in_disraptor-0.0.10.dist-info/top_level.txt
discourse_client_in_disraptor-0.0.10.dist-info/RECORD
